COPYING
MANIFEST.in
README.txt
setup.py
graphite_metrics/__init__.py
graphite_metrics/harvestd.py
graphite_metrics/harvestd.yaml
graphite_metrics.egg-info/PKG-INFO
graphite_metrics.egg-info/SOURCES.txt
graphite_metrics.egg-info/dependency_links.txt
graphite_metrics.egg-info/entry_points.txt
graphite_metrics.egg-info/requires.txt
graphite_metrics.egg-info/top_level.txt
graphite_metrics/collectors/__init__.py
graphite_metrics/collectors/_ping.py
graphite_metrics/collectors/cgacct.py
graphite_metrics/collectors/cjdns_peer_stats.py
graphite_metrics/collectors/cron_log.py
graphite_metrics/collectors/iptables_counts.py
graphite_metrics/collectors/irq.py
graphite_metrics/collectors/memfrag.py
graphite_metrics/collectors/memstats.py
graphite_metrics/collectors/ping.py
graphite_metrics/collectors/slabinfo.py
graphite_metrics/collectors/stats.py
graphite_metrics/collectors/sysstat.py
graphite_metrics/loops/__init__.py
graphite_metrics/loops/basic.py
graphite_metrics/processors/__init__.py
graphite_metrics/processors/hostname_prefix.py
graphite_metrics/sinks/__init__.py
graphite_metrics/sinks/carbon_socket.py
graphite_metrics/sinks/dump.py
graphite_metrics/sinks/librato_metrics.py