Metadata-Version: 1.1
Name: graphite-metrics
Version: 13.08.6
Summary: Standalone Graphite metric data collectors for various stuff thats not (or poorly) handled by other monitoring daemons
Home-page: http://github.com/mk-fg/graphite-metrics
Author: Mike Kazantsev
Author-email: mk.fraggod@gmail.com
License: WTFPL
Keywords: graphite sysstat systemd cgroups metrics proc
Platform: UNKNOWN
Classifier: Development Status :: 4 - Beta
Classifier: Environment :: No Input/Output (Daemon)
Classifier: Intended Audience :: Developers
Classifier: Intended Audience :: System Administrators
Classifier: Intended Audience :: Telecommunications Industry
Classifier: License :: OSI Approved
Classifier: Operating System :: POSIX
Classifier: Operating System :: Unix
Classifier: Programming Language :: Python
Classifier: Programming Language :: Python :: 2.7
Classifier: Programming Language :: Python :: 2 :: Only
Classifier: Topic :: Internet
Classifier: Topic :: Internet :: Log Analysis
Classifier: Topic :: System :: Monitoring
Classifier: Topic :: System :: Networking :: Monitoring
Classifier: Topic :: System :: Operating System Kernels :: Linux
